{"emily.taylor@gmail.com": 7, "emma.thomas@me.com": 4, "daniel.rodriguez@amerisave.com": 8, "michael.hall@dropbox.net": 4, "abigail.smith@amerisave.com": 6, "jackson.white@gmail.com": 6, "mason.robinson@amerisave.com": 1, "alexander.williams@gmail.com": 2, "olivia.wright@gmail.com": 6, "elizabeth.martinez@dropbox.net": 4, "nicholas.allen@microsoft.com": 2, "ethan.hernandez@microsoft.com": 3, "nathan.young@microsoft.com": 4, "mia.perez@me.com": 3, "isabella.jackson@amerisave.com": 4, "alexis.brown@microsoft.com": 2, "taylor.adams@gmail.com": 3, "sarah.green@amerisave.com": 2, "tyler.nelson@microsoft.com": 7, "chloe.garcia@dropbox.net": 1, "samantha.scott@me.com": 2, "jacob.lopez@dropbox.net": 3, "andrew.miller@gmail.com": 3, "ryan.king@dropbox.net": 3, "jack.thompson@me.com": 3, "alyssa.jones@amerisave.com": 2, "ava.davis@gmail.com": 3, "noah.sanchez@me.com": 3, "matthew.walker@amerisave.com": 0, "logan.clark@dropbox.net": 4, "sophia.baker@dropbox.net": 2, "dylan.wilson@gmail.com": 5, "ella.anderson@dropbox.net": 2, "grace.moore@gmail.com": 5, "aiden.johnson@microsoft.com": 5, "hannah.martin@dropbox.net": 3, "joshua.lee@gmail.com": 4, "madison.lewis@gmail.com": 0, "liam.gonzalez@me.com": 0, "lily.harris@gmail.com": 0}