{"jacob.lopez@dropbox.net": 10, "lily.harris@gmail.com": 11, "chloe.garcia@dropbox.net": 8, "nathan.young@microsoft.com": 18, "alexander.williams@gmail.com": 11, "logan.clark@dropbox.net": 11, "jack.thompson@me.com": 13, "noah.sanchez@me.com": 12, "andrew.miller@gmail.com": 14, "mia.perez@me.com": 15, "olivia.wright@gmail.com": 15, "michael.hall@dropbox.net": 17, "isabella.jackson@amerisave.com": 16, "ava.davis@gmail.com": 5, "sophia.baker@dropbox.net": 9, "mason.robinson@amerisave.com": 13, "matthew.walker@amerisave.com": 13, "taylor.adams@gmail.com": 11, "alexis.brown@microsoft.com": 14, "hannah.martin@dropbox.net": 6, "alyssa.jones@amerisave.com": 7, "samantha.scott@me.com": 19, "daniel.rodriguez@amerisave.com": 8, "madison.lewis@gmail.com": 12, "emily.taylor@gmail.com": 8, "elizabeth.martinez@dropbox.net": 11, "aiden.johnson@microsoft.com": 12, "ryan.king@dropbox.net": 17, "tyler.nelson@microsoft.com": 8, "ella.anderson@dropbox.net": 9, "grace.moore@gmail.com": 8, "liam.gonzalez@me.com": 11, "sarah.green@amerisave.com": 10, "nicholas.allen@microsoft.com": 16, "emma.thomas@me.com": 16, "joshua.lee@gmail.com": 6, "ethan.hernandez@microsoft.com": 7, "dylan.wilson@gmail.com": 11, "abigail.smith@amerisave.com": 8, "jackson.white@gmail.com": 10}